{
    "$schema": "vscode://schemas/color-theme",
    "name": "Base24 Equilibrium Gray Light",
    "type": "",
    "colors": {
        "terminal.background": "#f1f1f1",
        "terminal.foreground": "#474747",
        "terminal.ansiBrightBlack": "#d4d4d4",
        "terminal.ansiBrightRed": "#",
        "terminal.ansiBrightGreen": "#",
        "terminal.ansiBrightYellow": "#",
        "terminal.ansiBrightBlue": "#",
        "terminal.ansiBrightMagenta": "#",
        "terminal.ansiBrightCyan": "#",
        "terminal.ansiBrightWhite": "#1b1b1b",
        "terminal.ansiBlack": "#e2e2e2",
        "terminal.ansiRed": "#d02023",
        "terminal.ansiGreen": "#637200",
        "terminal.ansiYellow": "#bf3e05",
        "terminal.ansiBlue": "#0073b5",
        "terminal.ansiMagenta": "#4e66b6",
        "terminal.ansiCyan": "#007a72",
        "terminal.ansiWhite": "#303030",
        "terminal.border": "#474747",
        "terminal.selectionBackground": "#e2e2e250",
        "textBlockQuote.background": "#",
        "contrastBorder": "#",
        "focusBorder": "#777777",
        "foreground": "#474747",
        "widget.shadow": "#444444",
        "selection.background": "#0073b5",
        "errorForeground": "#d02023",
        "button.background": "#",
        "button.foreground": "#474747",
        "dropdown.background": "#f1f1f1",
        "dropdown.border": "#",
        "dropdown.foreground": "#474747",
        "input.background": "#f1f1f1",
        "input.foreground": "#474747",
        "input.border": "#",
        "input.placeholderForeground": "#777777",
        "inputOption.activeBorder": "#0073b5",
        "inputValidation.infoForeground": "#0073b5",
        "inputValidation.infoBackground": "#f1f1f1",
        "inputValidation.infoBorder": "#0073b5",
        "inputValidation.warningForeground": "#bf3e05",
        "inputValidation.warningBackground": "#f1f1f1",
        "inputValidation.warningBorder": "#bf3e05",
        "inputValidation.errorForeground": "#d02023",
        "inputValidation.errorBackground": "#f1f1f1",
        "inputValidation.errorBorder": "#d02023",
        "scrollbar.shadow": "#444444",
        "badge.foreground": "#474747",
        "badge.background": "#e2e2e2",
        "progressBar.background": "#4e66b6",
        "list.activeSelectionBackground": "#e2e2e2",
        "list.activeSelectionForeground": "#474747",
        "list.dropBackground": "#e2e2e2",
        "list.focusBackground": "#d4d4d475",
        "list.highlightForeground": "#007a72",
        "list.hoverBackground": "#d4d4d475",
        "list.inactiveSelectionBackground": "#d4d4d475",
        "list.warningForeground": "#bf3e05",
        "list.errorForeground": "#d02023",
        "activityBar.background": "#f1f1f1",
        "activityBar.inactiveForeground": "#777777",
        "activityBar.foreground": "#474747",
        "activityBar.activeBorder": "#4e66b680",
        "activityBar.activeBackground": "#0073b510",
        "activityBarBadge.background": "#4e66b6",
        "activityBarBadge.foreground": "#f1f1f1",
        "sideBar.background": "#",
        "sideBarTitle.foreground": "#474747",
        "sideBarSectionHeader.background": "#f1f1f1",
        "sideBarSectionHeader.border": "#",
        "editorGroup.border": "#0073b5",
        "editorGroup.dropBackground": "#d4d4d470",
        "editorGroupHeader.tabsBackground": "#",
        "tab.activeBackground": "#f1f1f1",
        "tab.activeForeground": "#474747",
        "tab.border": "#",
        "tab.activeBorderTop": "#4e66b680",
        "tab.inactiveBackground": "#",
        "tab.inactiveForeground": "#777777",
        "editor.foreground": "#474747",
        "editor.background": "#f1f1f1",
        "editorLineNumber.foreground": "#777777",
        "editor.selectionBackground": "#e2e2e2",
        "editor.selectionHighlightBackground": "#e2e2e2",
        "editor.foldBackground": "#",
        "editor.wordHighlightBackground": "#007a7250",
        "editor.wordHighlightStrongBackground": "#63720050",
        "editor.findMatchBackground": "#bf3e0580",
        "editor.findMatchHighlightBackground": "#1b1b1b40",
        "editor.findRangeHighlightBackground": "#d4d4d475",
        "editor.hoverHighlightBackground": "#",
        "editor.lineHighlightBorder": "#e2e2e2",
        "editorLink.activeForeground": "#007a72",
        "editor.rangeHighlightBackground": "#0073b515",
        "editor.snippetTabstopHighlightBackground": "#f1f1f1",
        "editor.snippetTabstopHighlightBorder": "#777777",
        "editor.snippetFinalTabstopHighlightBackground": "#f1f1f1",
        "editor.snippetFinalTabstopHighlightBorder": "#637200",
        "editorWhitespace.foreground": "#1b1b1b1A",
        "editorIndentGuide.background": "#1b1b1b1A",
        "editorIndentGuide.activeBackground": "#1b1b1b45",
        "editorRuler.foreground": "#1b1b1b1A",
        "editorCodeLens.foreground": "#777777",
        "editorOverviewRuler.border": "#",
        "editorOverviewRuler.selectionHighlightForeground": "#bf3e05",
        "editorOverviewRuler.wordHighlightForeground": "#007a72",
        "editorOverviewRuler.wordHighlightStrongForeground": "#637200",
        "editorOverviewRuler.modifiedForeground": "#007a7280",
        "editorOverviewRuler.addedForeground": "#63720080",
        "editorOverviewRuler.deletedForeground": "#d0202380",
        "editorOverviewRuler.errorForeground": "#d0202380",
        "editorOverviewRuler.warningForeground": "#bf3e0580",
        "editorOverviewRuler.infoForeground": "#007a7280",
        "editorError.foreground": "#d02023",
        "editorWarning.foreground": "#bf3e05",
        "editorGutter.modifiedBackground": "#007a7280",
        "editorGutter.addedBackground": "#63720080",
        "editorGutter.deletedBackground": "#d0202380",
        "gitDecoration.modifiedResourceForeground": "#007a72",
        "gitDecoration.deletedResourceForeground": "#d02023",
        "gitDecoration.untrackedResourceForeground": "#637200",
        "gitDecoration.ignoredResourceForeground": "#777777",
        "gitDecoration.conflictingResourceForeground": "#bf3e05",
        "diffEditor.insertedTextBackground": "#63720020",
        "diffEditor.removedTextBackground": "#d0202350",
        "editorWidget.background": "#",
        "editorSuggestWidget.background": "#",
        "editorSuggestWidget.foreground": "#474747",
        "editorSuggestWidget.selectedBackground": "#e2e2e2",
        "editorHoverWidget.background": "#f1f1f1",
        "editorHoverWidget.border": "#777777",
        "editorMarkerNavigation.background": "#",
        "peekView.border": "#e2e2e2",
        "peekViewEditor.background": "#f1f1f1",
        "peekViewEditor.matchHighlightBackground": "#80",
        "peekViewResult.background": "#",
        "peekViewResult.fileForeground": "#474747",
        "peekViewResult.lineForeground": "#474747",
        "peekViewResult.matchHighlightBackground": "#80",
        "peekViewResult.selectionBackground": "#e2e2e2",
        "peekViewResult.selectionForeground": "#474747",
        "peekViewTitle.background": "#",
        "peekViewTitleDescription.foreground": "#777777",
        "peekViewTitleLabel.foreground": "#474747",
        "merge.currentHeaderBackground": "#63720090",
        "merge.incomingHeaderBackground": "#0073b590",
        "editorOverviewRuler.currentContentForeground": "#637200",
        "editorOverviewRuler.incomingContentForeground": "#0073b5",
        "panel.background": "#f1f1f1",
        "panel.border": "#0073b5",
        "panelInput.border": "#474747",
        "panelTitle.activeBorder": "#4e66b6",
        "panelTitle.activeForeground": "#474747",
        "panelTitle.inactiveForeground": "#777777",
        "statusBar.background": "#",
        "statusBar.foreground": "#474747",
        "statusBar.debuggingBackground": "#d02023",
        "statusBar.debuggingForeground": "#",
        "statusBar.noFolderBackground": "#",
        "statusBar.noFolderForeground": "#474747",
        "statusBarItem.prominentBackground": "#d02023",
        "statusBarItem.prominentHoverBackground": "#bf3e05",
        "statusBarItem.remoteForeground": "#f1f1f1",
        "statusBarItem.remoteBackground": "#0073b5",
        "titleBar.activeBackground": "#",
        "titleBar.activeForeground": "#474747",
        "titleBar.inactiveBackground": "#",
        "titleBar.inactiveForeground": "#777777",
        "notificationCenter.border": "#",
        "notificationCenterHeader.foreground": "#474747",
        "notificationCenterHeader.background": "#f1f1f1",
        "notificationToast.border": "#",
        "notifications.foreground": "#474747",
        "notifications.background": "#f1f1f1",
        "notifications.border": "#",
        "notificationLink.foreground": "#007a72",
        "notificationsErrorIcon.foreground": "#d02023",
        "notificationsWarningIcon.foreground": "#bf3e05",
        "notificationsInfoIcon.foreground": "#0073b5",
        "notification.background": "#f1f1f1",
        "notification.foreground": "#474747",
        "notification.buttonBackground": "#e2e2e2",
        "notification.buttonForeground": "#474747",
        "notification.buttonHoverBackground": "#d4d4d475",
        "notification.errorBackground": "#d02023",
        "notification.errorForeground": "#f1f1f1",
        "notification.infoBackground": "#0073b5",
        "notification.infoForeground": "#f1f1f1",
        "notification.warningBackground": "#bf3e05",
        "notification.warningForeground": "#f1f1f1",
        "extensionButton.prominentForeground": "#474747",
        "extensionButton.prominentBackground": "#63720090",
        "extensionButton.prominentHoverBackground": "#63720060",
        "pickerGroup.border": "#0073b5",
        "pickerGroup.foreground": "#007a72",
        "debugToolBar.background": "#",
        "welcomePage.buttonBackground": "#e2e2e2",
        "welcomePage.buttonHoverBackground": "#d4d4d475",
        "walkThrough.embeddedEditorBackground": "#",
        "settings.headerForeground": "#474747",
        "settings.modifiedItemIndicator": "#bf3e05",
        "settings.dropdownBackground": "#",
        "settings.dropdownForeground": "#474747",
        "settings.dropdownBorder": "#",
        "settings.checkboxBackground": "#",
        "settings.checkboxForeground": "#474747",
        "settings.checkboxBorder": "#",
        "checkbox.background": "#",
        "checkbox.foreground": "#474747",
        "checkbox.border": "#",
        "settings.textInputBackground": "#",
        "settings.textInputForeground": "#474747",
        "settings.textInputBorder": "#",
        "settings.numberInputBackground": "#",
        "settings.numberInputForeground": "#474747",
        "settings.numberInputBorder": "#",
        "breadcrumb.foreground": "#777777",
        "breadcrumb.background": "#f1f1f1",
        "breadcrumb.focusForeground": "#474747",
        "breadcrumb.activeSelectionForeground": "#474747",
        "breadcrumbPicker.background": "#",
        "listFilterWidget.background": "#f1f1f1",
        "listFilterWidget.outline": "#e2e2e2",
        "listFilterWidget.noMatchesOutline": "#d02023"
    },
    "tokenColors": [
        {
            "scope": [
                "emphasis"
            ],
            "settings": {
                "fontStyle": "italic"
            }
        },
        {
            "scope": [
                "strong"
            ],
            "settings": {
                "fontStyle": "bold"
            }
        },
        {
            "scope": [
                "header"
            ],
            "settings": {
                "foreground": "#0073b5"
            }
        },
        {
            "scope": [
                "source"
            ],
            "settings": {
                "foreground": "#474747"
            }
        },
        {
            "scope": [
                "meta.diff",
                "meta.diff.header"
            ],
            "settings": {
                "foreground": "#777777"
            }
        },
        {
            "scope": [
                "markup.inserted"
            ],
            "settings": {
                "foreground": "#637200"
            }
        },
        {
            "scope": [
                "markup.deleted"
            ],
            "settings": {
                "foreground": "#d02023"
            }
        },
        {
            "scope": [
                "markup.changed"
            ],
            "settings": {
                "foreground": "#bf3e05"
            }
        },
        {
            "scope": [
                "invalid"
            ],
            "settings": {
                "foreground": "#d02023",
                "fontStyle": "underline italic"
            }
        },
        {
            "scope": [
                "invalid.deprecated"
            ],
            "settings": {
                "foreground": "#474747",
                "fontStyle": "underline italic"
            }
        },
        {
            "scope": [
                "entity.name.filename"
            ],
            "settings": {
                "foreground": "#"
            }
        },
        {
            "scope": [
                "markup.error"
            ],
            "settings": {
                "foreground": "#d02023"
            }
        },
        {
            "name": "Underlined markup",
            "scope": [
                "markup.underline"
            ],
            "settings": {
                "fontStyle": "underline"
            }
        },
        {
            "name": "Bold markup",
            "scope": [
                "markup.bold"
            ],
            "settings": {
                "fontStyle": "bold",
                "foreground": "#bf3e05"
            }
        },
        {
            "name": "Markup headings",
            "scope": [
                "markup.heading"
            ],
            "settings": {
                "fontStyle": "bold",
                "foreground": "#0073b5"
            }
        },
        {
            "name": "Markup italic",
            "scope": [
                "markup.italic"
            ],
            "settings": {
                "foreground": "#",
                "fontStyle": "italic"
            }
        },
        {
            "name": "Bullets, lists (prose)",
            "scope": [
                "beginning.punctuation.definition.list.markdown",
                "beginning.punctuation.definition.quote.markdown",
                "punctuation.definition.link.restructuredtext"
            ],
            "settings": {
                "foreground": "#007a72"
            }
        },
        {
            "name": "Inline code (prose)",
            "scope": [
                "markup.inline.raw",
                "markup.raw.restructuredtext"
            ],
            "settings": {
                "foreground": "#637200"
            }
        },
        {
            "name": "Links (prose)",
            "scope": [
                "markup.underline.link",
                "markup.underline.link.image"
            ],
            "settings": {
                "foreground": "#007a72"
            }
        },
        {
            "name": "Link text, image alt text (prose)",
            "scope": [
                "meta.link.reference.def.restructuredtext",
                "punctuation.definition.directive.restructuredtext",
                "string.other.link.description",
                "string.other.link.title"
            ],
            "settings": {
                "foreground": "#4e66b6"
            }
        },
        {
            "name": "Blockquotes (prose)",
            "scope": [
                "entity.name.directive.restructuredtext",
                "markup.quote"
            ],
            "settings": {
                "foreground": "#",
                "fontStyle": "italic"
            }
        },
        {
            "name": "Horizontal rule (prose)",
            "scope": [
                "meta.separator.markdown"
            ],
            "settings": {
                "foreground": "#777777"
            }
        },
        {
            "name": "Code blocks",
            "scope": [
                "fenced_code.block.language",
                "markup.raw.inner.restructuredtext",
                "markup.fenced_code.block.markdown punctuation.definition.markdown"
            ],
            "settings": {
                "foreground": "#637200"
            }
        },
        {
            "name": "Prose constants",
            "scope": [
                "punctuation.definition.constant.restructuredtext"
            ],
            "settings": {
                "foreground": "#0073b5"
            }
        },
        {
            "name": "Braces in markdown headings",
            "scope": [
                "markup.heading.markdown punctuation.definition.string.begin",
                "markup.heading.markdown punctuation.definition.string.end"
            ],
            "settings": {
                "foreground": "#0073b5"
            }
        },
        {
            "name": "Braces in markdown paragraphs",
            "scope": [
                "meta.paragraph.markdown punctuation.definition.string.begin",
                "meta.paragraph.markdown punctuation.definition.string.end"
            ],
            "settings": {
                "foreground": "#474747"
            }
        },
        {
            "name": "Braces in markdown blockquotes",
            "scope": [
                "markup.quote.markdown meta.paragraph.markdown punctuation.definition.string.begin",
                "markup.quote.markdown meta.paragraph.markdown punctuation.definition.string.end"
            ],
            "settings": {
                "foreground": "#"
            }
        },
        {
            "name": "User-defined class names",
            "scope": [
                "entity.name.type.class",
                "entity.name.class"
            ],
            "settings": {
                "foreground": "#007a72",
                "fontStyle": "normal"
            }
        },
        {
            "name": "this, super, self, etc.",
            "scope": [
                "keyword.expressions-and-types.swift",
                "keyword.other.this",
                "variable.language",
                "variable.language punctuation.definition.variable.php",
                "variable.other.readwrite.instance.ruby",
                "variable.parameter.function.language.special"
            ],
            "settings": {
                "foreground": "#0073b5",
                "fontStyle": "italic"
            }
        },
        {
            "name": "Inherited classes",
            "scope": [
                "entity.other.inherited-class"
            ],
            "settings": {
                "fontStyle": "italic",
                "foreground": "#007a72"
            }
        },
        {
            "name": "Comments",
            "scope": [
                "comment",
                "punctuation.definition.comment",
                "unused.comment",
                "wildcard.comment"
            ],
            "settings": {
                "foreground": "#777777"
            }
        },
        {
            "name": "JSDoc-style keywords",
            "scope": [
                "comment keyword.codetag.notation",
                "comment.block.documentation keyword",
                "comment.block.documentation storage.type.class"
            ],
            "settings": {
                "foreground": "#4e66b6"
            }
        },
        {
            "name": "JSDoc-style types",
            "scope": [
                "comment.block.documentation entity.name.type"
            ],
            "settings": {
                "foreground": "#007a72",
                "fontStyle": "italic"
            }
        },
        {
            "name": "JSDoc-style type brackets",
            "scope": [
                "comment.block.documentation entity.name.type punctuation.definition.bracket"
            ],
            "settings": {
                "foreground": "#007a72"
            }
        },
        {
            "name": "JSDoc-style comment parameters",
            "scope": [
                "comment.block.documentation variable"
            ],
            "settings": {
                "foreground": "#bf3e05",
                "fontStyle": "italic"
            }
        },
        {
            "name": "Constants",
            "scope": [
                "constant",
                "variable.other.constant"
            ],
            "settings": {
                "foreground": "#0073b5"
            }
        },
        {
            "name": "Constant escape sequences",
            "scope": [
                "constant.character.escape",
                "constant.character.string.escape",
                "constant.regexp"
            ],
            "settings": {
                "foreground": "#4e66b6"
            }
        },
        {
            "name": "HTML tags",
            "scope": [
                "entity.name.tag"
            ],
            "settings": {
                "foreground": "#4e66b6"
            }
        },
        {
            "name": "CSS attribute parent selectors ('&')",
            "scope": [
                "entity.other.attribute-name.parent-selector"
            ],
            "settings": {
                "foreground": "#4e66b6"
            }
        },
        {
            "name": "HTML/CSS attribute names",
            "scope": [
                "entity.other.attribute-name"
            ],
            "settings": {
                "foreground": "#637200",
                "fontStyle": "italic"
            }
        },
        {
            "name": "Function names",
            "scope": [
                "entity.name.function",
                "meta.function-call.generic",
                "meta.function-call.object",
                "meta.function-call.php",
                "meta.function-call.static",
                "meta.method-call.java meta.method",
                "meta.method.groovy",
                "support.function.any-method.lua",
                "keyword.operator.function.infix"
            ],
            "settings": {
                "foreground": "#637200"
            }
        },
        {
            "name": "Function parameters",
            "scope": [
                "entity.name.variable.parameter",
                "meta.at-rule.function variable",
                "meta.at-rule.mixin variable",
                "meta.function.arguments variable.other.php",
                "meta.selectionset.graphql meta.arguments.graphql variable.arguments.graphql",
                "variable.parameter"
            ],
            "settings": {
                "fontStyle": "italic",
                "foreground": "#bf3e05"
            }
        },
        {
            "name": "Decorators",
            "scope": [
                "meta.decorator variable.other.readwrite",
                "meta.decorator variable.other.property"
            ],
            "settings": {
                "foreground": "#637200",
                "fontStyle": "italic"
            }
        },
        {
            "name": "Decorator Objects",
            "scope": [
                "meta.decorator variable.other.object"
            ],
            "settings": {
                "foreground": "#637200"
            }
        },
        {
            "name": "Keywords",
            "scope": [
                "keyword",
                "punctuation.definition.keyword"
            ],
            "settings": {
                "foreground": "#4e66b6"
            }
        },
        {
            "name": "Keyword \"new\"",
            "scope": [
                "keyword.control.new",
                "keyword.operator.new"
            ],
            "settings": {
                "fontStyle": "bold"
            }
        },
        {
            "name": "Generic selectors (CSS/SCSS/Less/Stylus)",
            "scope": [
                "meta.selector"
            ],
            "settings": {
                "foreground": "#4e66b6"
            }
        },
        {
            "name": "Language Built-ins",
            "scope": [
                "support"
            ],
            "settings": {
                "fontStyle": "italic",
                "foreground": "#007a72"
            }
        },
        {
            "name": "Built-in magic functions and constants",
            "scope": [
                "support.function.magic",
                "support.variable",
                "variable.other.predefined"
            ],
            "settings": {
                "fontStyle": "regular",
                "foreground": "#0073b5"
            }
        },
        {
            "name": "Built-in functions / properties",
            "scope": [
                "support.function",
                "support.type.property-name"
            ],
            "settings": {
                "fontStyle": "regular"
            }
        },
        {
            "name": "Separators (key/value, namespace, inheritance, pointer, hash, slice, etc)",
            "scope": [
                "constant.other.symbol.hashkey punctuation.definition.constant.ruby",
                "entity.other.attribute-name.placeholder punctuation",
                "entity.other.attribute-name.pseudo-class punctuation",
                "entity.other.attribute-name.pseudo-element punctuation",
                "meta.group.double.toml",
                "meta.group.toml",
                "meta.object-binding-pattern-variable punctuation.destructuring",
                "punctuation.colon.graphql",
                "punctuation.definition.block.scalar.folded.yaml",
                "punctuation.definition.block.scalar.literal.yaml",
                "punctuation.definition.block.sequence.item.yaml",
                "punctuation.definition.entity.other.inherited-class",
                "punctuation.function.swift",
                "punctuation.separator.dictionary.key-value",
                "punctuation.separator.hash",
                "punctuation.separator.inheritance",
                "punctuation.separator.key-value",
                "punctuation.separator.key-value.mapping.yaml",
                "punctuation.separator.namespace",
                "punctuation.separator.pointer-access",
                "punctuation.separator.slice",
                "string.unquoted.heredoc punctuation.definition.string",
                "support.other.chomping-indicator.yaml",
                "punctuation.separator.annotation"
            ],
            "settings": {
                "foreground": "#4e66b6"
            }
        },
        {
            "name": "Brackets, braces, parens, etc.",
            "scope": [
                "keyword.operator.other.powershell",
                "keyword.other.statement-separator.powershell",
                "meta.brace.round",
                "meta.function-call punctuation",
                "punctuation.definition.arguments.begin",
                "punctuation.definition.arguments.end",
                "punctuation.definition.entity.begin",
                "punctuation.definition.entity.end",
                "punctuation.definition.tag.cs",
                "punctuation.definition.type.begin",
                "punctuation.definition.type.end",
                "punctuation.section.scope.begin",
                "punctuation.section.scope.end",
                "storage.type.generic.java",
                "string.template meta.brace",
                "string.template punctuation.accessor"
            ],
            "settings": {
                "foreground": "#474747"
            }
        },
        {
            "name": "Variable interpolation operators",
            "scope": [
                "meta.string-contents.quoted.double punctuation.definition.variable",
                "punctuation.definition.interpolation.begin",
                "punctuation.definition.interpolation.end",
                "punctuation.definition.template-expression.begin",
                "punctuation.definition.template-expression.end",
                "punctuation.section.embedded.begin",
                "punctuation.section.embedded.coffee",
                "punctuation.section.embedded.end",
                "punctuation.section.embedded.end source.php",
                "punctuation.section.embedded.end source.ruby",
                "punctuation.definition.variable.makefile"
            ],
            "settings": {
                "foreground": "#4e66b6"
            }
        },
        {
            "name": "Keys (serializable languages)",
            "scope": [
                "entity.name.function.target.makefile",
                "entity.name.section.toml",
                "entity.name.tag.yaml",
                "variable.other.key.toml"
            ],
            "settings": {
                "foreground": "#007a72"
            }
        },
        {
            "name": "Dates / timestamps (serializable languages)",
            "scope": [
                "constant.other.date",
                "constant.other.timestamp"
            ],
            "settings": {
                "foreground": "#bf3e05"
            }
        },
        {
            "name": "YAML aliases",
            "scope": [
                "variable.other.alias.yaml"
            ],
            "settings": {
                "fontStyle": "italic underline",
                "foreground": "#637200"
            }
        },
        {
            "name": "Storage",
            "scope": [
                "storage",
                "meta.implementation storage.type.objc",
                "meta.interface-or-protocol storage.type.objc",
                "source.groovy storage.type.def"
            ],
            "settings": {
                "fontStyle": "regular",
                "foreground": "#4e66b6"
            }
        },
        {
            "name": "Types",
            "scope": [
                "entity.name.type",
                "keyword.primitive-datatypes.swift",
                "keyword.type.cs",
                "meta.protocol-list.objc",
                "meta.return-type.objc",
                "source.go storage.type",
                "source.groovy storage.type",
                "source.java storage.type",
                "source.powershell entity.other.attribute-name",
                "storage.class.std.rust",
                "storage.type.attribute.swift",
                "storage.type.c",
                "storage.type.core.rust",
                "storage.type.cs",
                "storage.type.groovy",
                "storage.type.objc",
                "storage.type.php",
                "storage.type.haskell",
                "storage.type.ocaml"
            ],
            "settings": {
                "fontStyle": "italic",
                "foreground": "#007a72"
            }
        },
        {
            "name": "Generics, templates, and mapped type declarations",
            "scope": [
                "entity.name.type.type-parameter",
                "meta.indexer.mappedtype.declaration entity.name.type",
                "meta.type.parameters entity.name.type"
            ],
            "settings": {
                "foreground": "#bf3e05"
            }
        },
        {
            "name": "Modifiers",
            "scope": [
                "storage.modifier"
            ],
            "settings": {
                "foreground": "#4e66b6"
            }
        },
        {
            "name": "RegExp string",
            "scope": [
                "string.regexp",
                "constant.other.character-class.set.regexp",
                "constant.character.escape.backslash.regexp"
            ],
            "settings": {
                "foreground": "#"
            }
        },
        {
            "name": "Non-capture operators",
            "scope": [
                "punctuation.definition.group.capture.regexp"
            ],
            "settings": {
                "foreground": "#4e66b6"
            }
        },
        {
            "name": "RegExp start and end characters",
            "scope": [
                "string.regexp punctuation.definition.string.begin",
                "string.regexp punctuation.definition.string.end"
            ],
            "settings": {
                "foreground": "#d02023"
            }
        },
        {
            "name": "Character group",
            "scope": [
                "punctuation.definition.character-class.regexp"
            ],
            "settings": {
                "foreground": "#007a72"
            }
        },
        {
            "name": "Capture groups",
            "scope": [
                "punctuation.definition.group.regexp"
            ],
            "settings": {
                "foreground": "#bf3e05"
            }
        },
        {
            "name": "Assertion operators",
            "scope": [
                "punctuation.definition.group.assertion.regexp",
                "keyword.operator.negation.regexp"
            ],
            "settings": {
                "foreground": "#d02023"
            }
        },
        {
            "name": "Positive lookaheads",
            "scope": [
                "meta.assertion.look-ahead.regexp"
            ],
            "settings": {
                "foreground": "#637200"
            }
        },
        {
            "name": "Strings",
            "scope": [
                "string"
            ],
            "settings": {
                "foreground": "#"
            }
        },
        {
            "name": "String quotes (temporary vscode fix)",
            "scope": [
                "punctuation.definition.string.begin",
                "punctuation.definition.string.end"
            ],
            "settings": {
                "foreground": "#9d6f00"
            }
        },
        {
            "name": "Property quotes (temporary vscode fix)",
            "scope": [
                "punctuation.support.type.property-name.begin",
                "punctuation.support.type.property-name.end"
            ],
            "settings": {
                "foreground": "#0073b5"
            }
        },
        {
            "name": "Docstrings",
            "scope": [
                "string.quoted.docstring.multi",
                "string.quoted.docstring.multi.python punctuation.definition.string.begin",
                "string.quoted.docstring.multi.python punctuation.definition.string.end",
                "string.quoted.docstring.multi.python constant.character.escape"
            ],
            "settings": {
                "foreground": "#777777"
            }
        },
        {
            "name": "Variables and object properties",
            "scope": [
                "variable",
                "constant.other.key.perl",
                "support.variable.property",
                "variable.other.constant.js",
                "variable.other.constant.ts",
                "variable.other.constant.tsx"
            ],
            "settings": {
                "foreground": "#474747"
            }
        },
        {
            "name": "Destructuring / aliasing reference name (LHS)",
            "scope": [
                "meta.import variable.other.readwrite",
                "meta.object-binding-pattern-variable variable.object.property",
                "meta.variable.assignment.destructured.object.coffee variable"
            ],
            "settings": {
                "fontStyle": "italic",
                "foreground": "#bf3e05"
            }
        },
        {
            "name": "Destructuring / aliasing variable name (RHS)",
            "scope": [
                "meta.import variable.other.readwrite.alias",
                "meta.export variable.other.readwrite.alias",
                "meta.variable.assignment.destructured.object.coffee variable variable"
            ],
            "settings": {
                "fontStyle": "normal",
                "foreground": "#474747"
            }
        },
        {
            "name": "GraphQL keys",
            "scope": [
                "meta.selectionset.graphql variable"
            ],
            "settings": {
                "foreground": "#"
            }
        },
        {
            "name": "GraphQL function arguments",
            "scope": [
                "meta.selectionset.graphql meta.arguments variable"
            ],
            "settings": {
                "foreground": "#474747"
            }
        },
        {
            "name": "GraphQL fragment name (definition)",
            "scope": [
                "entity.name.fragment.graphql",
                "variable.fragment.graphql"
            ],
            "settings": {
                "foreground": "#007a72"
            }
        },
        {
            "name": "Edge cases (foreground color resets)",
            "scope": [
                "constant.other.symbol.hashkey.ruby",
                "keyword.operator.dereference.java",
                "keyword.operator.navigation.groovy",
                "meta.scope.for-loop.shell punctuation.definition.string.begin",
                "meta.scope.for-loop.shell punctuation.definition.string.end",
                "meta.scope.for-loop.shell string",
                "storage.modifier.import",
                "punctuation.section.embedded.begin.tsx",
                "punctuation.section.embedded.end.tsx",
                "punctuation.section.embedded.begin.jsx",
                "punctuation.section.embedded.end.jsx",
                "punctuation.separator.list.comma.css",
                "constant.language.empty-list.haskell"
            ],
            "settings": {
                "foreground": "#474747"
            }
        },
        {
            "name": "Shell variables prefixed with \"$\" (edge case)",
            "scope": [
                "source.shell variable.other"
            ],
            "settings": {
                "foreground": "#0073b5"
            }
        },
        {
            "name": "Powershell constants mistakenly scoped to `support`, rather than `constant` (edge)",
            "scope": [
                "support.constant"
            ],
            "settings": {
                "fontStyle": "normal",
                "foreground": "#0073b5"
            }
        },
        {
            "name": "Makefile prerequisite names",
            "scope": [
                "meta.scope.prerequisites.makefile"
            ],
            "settings": {
                "foreground": "#"
            }
        },
        {
            "name": "SCSS attibute selector strings",
            "scope": [
                "meta.attribute-selector.scss"
            ],
            "settings": {
                "foreground": "#"
            }
        },
        {
            "name": "SCSS attribute selector brackets",
            "scope": [
                "punctuation.definition.attribute-selector.end.bracket.square.scss",
                "punctuation.definition.attribute-selector.begin.bracket.square.scss"
            ],
            "settings": {
                "foreground": "#474747"
            }
        },
        {
            "name": "Haskell Pragmas",
            "scope": [
                "meta.preprocessor.haskell"
            ],
            "settings": {
                "foreground": "#777777"
            }
        }
    ]
}
