{
    "$schema": "vscode://schemas/color-theme",
    "name": "Base24 Vice Dark",
    "type": "",
    "colors": {
        "terminal.background": "#181818",
        "terminal.foreground": "#818181",
        "terminal.ansiBrightBlack": "#323232",
        "terminal.ansiBrightRed": "#",
        "terminal.ansiBrightGreen": "#",
        "terminal.ansiBrightYellow": "#",
        "terminal.ansiBrightBlue": "#",
        "terminal.ansiBrightMagenta": "#",
        "terminal.ansiBrightCyan": "#",
        "terminal.ansiBrightWhite": "#e9e9e9",
        "terminal.ansiBlack": "#222222",
        "terminal.ansiRed": "#ff29a8",
        "terminal.ansiGreen": "#0badff",
        "terminal.ansiYellow": "#85ffe0",
        "terminal.ansiBlue": "#00eaff",
        "terminal.ansiMagenta": "#00f6d9",
        "terminal.ansiCyan": "#8265ff",
        "terminal.ansiWhite": "#c6c6c6",
        "terminal.border": "#818181",
        "terminal.selectionBackground": "#22222250",
        "textBlockQuote.background": "#",
        "contrastBorder": "#",
        "focusBorder": "#3f3f3f",
        "foreground": "#818181",
        "widget.shadow": "#444444",
        "selection.background": "#00eaff",
        "errorForeground": "#ff29a8",
        "button.background": "#",
        "button.foreground": "#818181",
        "dropdown.background": "#181818",
        "dropdown.border": "#",
        "dropdown.foreground": "#818181",
        "input.background": "#181818",
        "input.foreground": "#818181",
        "input.border": "#",
        "input.placeholderForeground": "#3f3f3f",
        "inputOption.activeBorder": "#00eaff",
        "inputValidation.infoForeground": "#00eaff",
        "inputValidation.infoBackground": "#181818",
        "inputValidation.infoBorder": "#00eaff",
        "inputValidation.warningForeground": "#85ffe0",
        "inputValidation.warningBackground": "#181818",
        "inputValidation.warningBorder": "#85ffe0",
        "inputValidation.errorForeground": "#ff29a8",
        "inputValidation.errorBackground": "#181818",
        "inputValidation.errorBorder": "#ff29a8",
        "scrollbar.shadow": "#444444",
        "badge.foreground": "#818181",
        "badge.background": "#222222",
        "progressBar.background": "#00f6d9",
        "list.activeSelectionBackground": "#222222",
        "list.activeSelectionForeground": "#818181",
        "list.dropBackground": "#222222",
        "list.focusBackground": "#32323275",
        "list.highlightForeground": "#8265ff",
        "list.hoverBackground": "#32323275",
        "list.inactiveSelectionBackground": "#32323275",
        "list.warningForeground": "#85ffe0",
        "list.errorForeground": "#ff29a8",
        "activityBar.background": "#181818",
        "activityBar.inactiveForeground": "#3f3f3f",
        "activityBar.foreground": "#818181",
        "activityBar.activeBorder": "#00f6d980",
        "activityBar.activeBackground": "#00eaff10",
        "activityBarBadge.background": "#00f6d9",
        "activityBarBadge.foreground": "#181818",
        "sideBar.background": "#",
        "sideBarTitle.foreground": "#818181",
        "sideBarSectionHeader.background": "#181818",
        "sideBarSectionHeader.border": "#",
        "editorGroup.border": "#00eaff",
        "editorGroup.dropBackground": "#32323270",
        "editorGroupHeader.tabsBackground": "#",
        "tab.activeBackground": "#181818",
        "tab.activeForeground": "#818181",
        "tab.border": "#",
        "tab.activeBorderTop": "#00f6d980",
        "tab.inactiveBackground": "#",
        "tab.inactiveForeground": "#3f3f3f",
        "editor.foreground": "#818181",
        "editor.background": "#181818",
        "editorLineNumber.foreground": "#3f3f3f",
        "editor.selectionBackground": "#222222",
        "editor.selectionHighlightBackground": "#222222",
        "editor.foldBackground": "#",
        "editor.wordHighlightBackground": "#8265ff50",
        "editor.wordHighlightStrongBackground": "#0badff50",
        "editor.findMatchBackground": "#85ffe080",
        "editor.findMatchHighlightBackground": "#e9e9e940",
        "editor.findRangeHighlightBackground": "#32323275",
        "editor.hoverHighlightBackground": "#",
        "editor.lineHighlightBorder": "#222222",
        "editorLink.activeForeground": "#8265ff",
        "editor.rangeHighlightBackground": "#00eaff15",
        "editor.snippetTabstopHighlightBackground": "#181818",
        "editor.snippetTabstopHighlightBorder": "#3f3f3f",
        "editor.snippetFinalTabstopHighlightBackground": "#181818",
        "editor.snippetFinalTabstopHighlightBorder": "#0badff",
        "editorWhitespace.foreground": "#e9e9e91A",
        "editorIndentGuide.background": "#e9e9e91A",
        "editorIndentGuide.activeBackground": "#e9e9e945",
        "editorRuler.foreground": "#e9e9e91A",
        "editorCodeLens.foreground": "#3f3f3f",
        "editorOverviewRuler.border": "#",
        "editorOverviewRuler.selectionHighlightForeground": "#85ffe0",
        "editorOverviewRuler.wordHighlightForeground": "#8265ff",
        "editorOverviewRuler.wordHighlightStrongForeground": "#0badff",
        "editorOverviewRuler.modifiedForeground": "#8265ff80",
        "editorOverviewRuler.addedForeground": "#0badff80",
        "editorOverviewRuler.deletedForeground": "#ff29a880",
        "editorOverviewRuler.errorForeground": "#ff29a880",
        "editorOverviewRuler.warningForeground": "#85ffe080",
        "editorOverviewRuler.infoForeground": "#8265ff80",
        "editorError.foreground": "#ff29a8",
        "editorWarning.foreground": "#85ffe0",
        "editorGutter.modifiedBackground": "#8265ff80",
        "editorGutter.addedBackground": "#0badff80",
        "editorGutter.deletedBackground": "#ff29a880",
        "gitDecoration.modifiedResourceForeground": "#8265ff",
        "gitDecoration.deletedResourceForeground": "#ff29a8",
        "gitDecoration.untrackedResourceForeground": "#0badff",
        "gitDecoration.ignoredResourceForeground": "#3f3f3f",
        "gitDecoration.conflictingResourceForeground": "#85ffe0",
        "diffEditor.insertedTextBackground": "#0badff20",
        "diffEditor.removedTextBackground": "#ff29a850",
        "editorWidget.background": "#",
        "editorSuggestWidget.background": "#",
        "editorSuggestWidget.foreground": "#818181",
        "editorSuggestWidget.selectedBackground": "#222222",
        "editorHoverWidget.background": "#181818",
        "editorHoverWidget.border": "#3f3f3f",
        "editorMarkerNavigation.background": "#",
        "peekView.border": "#222222",
        "peekViewEditor.background": "#181818",
        "peekViewEditor.matchHighlightBackground": "#80",
        "peekViewResult.background": "#",
        "peekViewResult.fileForeground": "#818181",
        "peekViewResult.lineForeground": "#818181",
        "peekViewResult.matchHighlightBackground": "#80",
        "peekViewResult.selectionBackground": "#222222",
        "peekViewResult.selectionForeground": "#818181",
        "peekViewTitle.background": "#",
        "peekViewTitleDescription.foreground": "#3f3f3f",
        "peekViewTitleLabel.foreground": "#818181",
        "merge.currentHeaderBackground": "#0badff90",
        "merge.incomingHeaderBackground": "#00eaff90",
        "editorOverviewRuler.currentContentForeground": "#0badff",
        "editorOverviewRuler.incomingContentForeground": "#00eaff",
        "panel.background": "#181818",
        "panel.border": "#00eaff",
        "panelInput.border": "#818181",
        "panelTitle.activeBorder": "#00f6d9",
        "panelTitle.activeForeground": "#818181",
        "panelTitle.inactiveForeground": "#3f3f3f",
        "statusBar.background": "#",
        "statusBar.foreground": "#818181",
        "statusBar.debuggingBackground": "#ff29a8",
        "statusBar.debuggingForeground": "#",
        "statusBar.noFolderBackground": "#",
        "statusBar.noFolderForeground": "#818181",
        "statusBarItem.prominentBackground": "#ff29a8",
        "statusBarItem.prominentHoverBackground": "#85ffe0",
        "statusBarItem.remoteForeground": "#181818",
        "statusBarItem.remoteBackground": "#00eaff",
        "titleBar.activeBackground": "#",
        "titleBar.activeForeground": "#818181",
        "titleBar.inactiveBackground": "#",
        "titleBar.inactiveForeground": "#3f3f3f",
        "notificationCenter.border": "#",
        "notificationCenterHeader.foreground": "#818181",
        "notificationCenterHeader.background": "#181818",
        "notificationToast.border": "#",
        "notifications.foreground": "#818181",
        "notifications.background": "#181818",
        "notifications.border": "#",
        "notificationLink.foreground": "#8265ff",
        "notificationsErrorIcon.foreground": "#ff29a8",
        "notificationsWarningIcon.foreground": "#85ffe0",
        "notificationsInfoIcon.foreground": "#00eaff",
        "notification.background": "#181818",
        "notification.foreground": "#818181",
        "notification.buttonBackground": "#222222",
        "notification.buttonForeground": "#818181",
        "notification.buttonHoverBackground": "#32323275",
        "notification.errorBackground": "#ff29a8",
        "notification.errorForeground": "#181818",
        "notification.infoBackground": "#00eaff",
        "notification.infoForeground": "#181818",
        "notification.warningBackground": "#85ffe0",
        "notification.warningForeground": "#181818",
        "extensionButton.prominentForeground": "#818181",
        "extensionButton.prominentBackground": "#0badff90",
        "extensionButton.prominentHoverBackground": "#0badff60",
        "pickerGroup.border": "#00eaff",
        "pickerGroup.foreground": "#8265ff",
        "debugToolBar.background": "#",
        "welcomePage.buttonBackground": "#222222",
        "welcomePage.buttonHoverBackground": "#32323275",
        "walkThrough.embeddedEditorBackground": "#",
        "settings.headerForeground": "#818181",
        "settings.modifiedItemIndicator": "#85ffe0",
        "settings.dropdownBackground": "#",
        "settings.dropdownForeground": "#818181",
        "settings.dropdownBorder": "#",
        "settings.checkboxBackground": "#",
        "settings.checkboxForeground": "#818181",
        "settings.checkboxBorder": "#",
        "checkbox.background": "#",
        "checkbox.foreground": "#818181",
        "checkbox.border": "#",
        "settings.textInputBackground": "#",
        "settings.textInputForeground": "#818181",
        "settings.textInputBorder": "#",
        "settings.numberInputBackground": "#",
        "settings.numberInputForeground": "#818181",
        "settings.numberInputBorder": "#",
        "breadcrumb.foreground": "#3f3f3f",
        "breadcrumb.background": "#181818",
        "breadcrumb.focusForeground": "#818181",
        "breadcrumb.activeSelectionForeground": "#818181",
        "breadcrumbPicker.background": "#",
        "listFilterWidget.background": "#181818",
        "listFilterWidget.outline": "#222222",
        "listFilterWidget.noMatchesOutline": "#ff29a8"
    },
    "tokenColors": [
        {
            "scope": [
                "emphasis"
            ],
            "settings": {
                "fontStyle": "italic"
            }
        },
        {
            "scope": [
                "strong"
            ],
            "settings": {
                "fontStyle": "bold"
            }
        },
        {
            "scope": [
                "header"
            ],
            "settings": {
                "foreground": "#00eaff"
            }
        },
        {
            "scope": [
                "source"
            ],
            "settings": {
                "foreground": "#818181"
            }
        },
        {
            "scope": [
                "meta.diff",
                "meta.diff.header"
            ],
            "settings": {
                "foreground": "#3f3f3f"
            }
        },
        {
            "scope": [
                "markup.inserted"
            ],
            "settings": {
                "foreground": "#0badff"
            }
        },
        {
            "scope": [
                "markup.deleted"
            ],
            "settings": {
                "foreground": "#ff29a8"
            }
        },
        {
            "scope": [
                "markup.changed"
            ],
            "settings": {
                "foreground": "#85ffe0"
            }
        },
        {
            "scope": [
                "invalid"
            ],
            "settings": {
                "foreground": "#ff29a8",
                "fontStyle": "underline italic"
            }
        },
        {
            "scope": [
                "invalid.deprecated"
            ],
            "settings": {
                "foreground": "#818181",
                "fontStyle": "underline italic"
            }
        },
        {
            "scope": [
                "entity.name.filename"
            ],
            "settings": {
                "foreground": "#"
            }
        },
        {
            "scope": [
                "markup.error"
            ],
            "settings": {
                "foreground": "#ff29a8"
            }
        },
        {
            "name": "Underlined markup",
            "scope": [
                "markup.underline"
            ],
            "settings": {
                "fontStyle": "underline"
            }
        },
        {
            "name": "Bold markup",
            "scope": [
                "markup.bold"
            ],
            "settings": {
                "fontStyle": "bold",
                "foreground": "#85ffe0"
            }
        },
        {
            "name": "Markup headings",
            "scope": [
                "markup.heading"
            ],
            "settings": {
                "fontStyle": "bold",
                "foreground": "#00eaff"
            }
        },
        {
            "name": "Markup italic",
            "scope": [
                "markup.italic"
            ],
            "settings": {
                "foreground": "#",
                "fontStyle": "italic"
            }
        },
        {
            "name": "Bullets, lists (prose)",
            "scope": [
                "beginning.punctuation.definition.list.markdown",
                "beginning.punctuation.definition.quote.markdown",
                "punctuation.definition.link.restructuredtext"
            ],
            "settings": {
                "foreground": "#8265ff"
            }
        },
        {
            "name": "Inline code (prose)",
            "scope": [
                "markup.inline.raw",
                "markup.raw.restructuredtext"
            ],
            "settings": {
                "foreground": "#0badff"
            }
        },
        {
            "name": "Links (prose)",
            "scope": [
                "markup.underline.link",
                "markup.underline.link.image"
            ],
            "settings": {
                "foreground": "#8265ff"
            }
        },
        {
            "name": "Link text, image alt text (prose)",
            "scope": [
                "meta.link.reference.def.restructuredtext",
                "punctuation.definition.directive.restructuredtext",
                "string.other.link.description",
                "string.other.link.title"
            ],
            "settings": {
                "foreground": "#00f6d9"
            }
        },
        {
            "name": "Blockquotes (prose)",
            "scope": [
                "entity.name.directive.restructuredtext",
                "markup.quote"
            ],
            "settings": {
                "foreground": "#",
                "fontStyle": "italic"
            }
        },
        {
            "name": "Horizontal rule (prose)",
            "scope": [
                "meta.separator.markdown"
            ],
            "settings": {
                "foreground": "#3f3f3f"
            }
        },
        {
            "name": "Code blocks",
            "scope": [
                "fenced_code.block.language",
                "markup.raw.inner.restructuredtext",
                "markup.fenced_code.block.markdown punctuation.definition.markdown"
            ],
            "settings": {
                "foreground": "#0badff"
            }
        },
        {
            "name": "Prose constants",
            "scope": [
                "punctuation.definition.constant.restructuredtext"
            ],
            "settings": {
                "foreground": "#00eaff"
            }
        },
        {
            "name": "Braces in markdown headings",
            "scope": [
                "markup.heading.markdown punctuation.definition.string.begin",
                "markup.heading.markdown punctuation.definition.string.end"
            ],
            "settings": {
                "foreground": "#00eaff"
            }
        },
        {
            "name": "Braces in markdown paragraphs",
            "scope": [
                "meta.paragraph.markdown punctuation.definition.string.begin",
                "meta.paragraph.markdown punctuation.definition.string.end"
            ],
            "settings": {
                "foreground": "#818181"
            }
        },
        {
            "name": "Braces in markdown blockquotes",
            "scope": [
                "markup.quote.markdown meta.paragraph.markdown punctuation.definition.string.begin",
                "markup.quote.markdown meta.paragraph.markdown punctuation.definition.string.end"
            ],
            "settings": {
                "foreground": "#"
            }
        },
        {
            "name": "User-defined class names",
            "scope": [
                "entity.name.type.class",
                "entity.name.class"
            ],
            "settings": {
                "foreground": "#8265ff",
                "fontStyle": "normal"
            }
        },
        {
            "name": "this, super, self, etc.",
            "scope": [
                "keyword.expressions-and-types.swift",
                "keyword.other.this",
                "variable.language",
                "variable.language punctuation.definition.variable.php",
                "variable.other.readwrite.instance.ruby",
                "variable.parameter.function.language.special"
            ],
            "settings": {
                "foreground": "#00eaff",
                "fontStyle": "italic"
            }
        },
        {
            "name": "Inherited classes",
            "scope": [
                "entity.other.inherited-class"
            ],
            "settings": {
                "fontStyle": "italic",
                "foreground": "#8265ff"
            }
        },
        {
            "name": "Comments",
            "scope": [
                "comment",
                "punctuation.definition.comment",
                "unused.comment",
                "wildcard.comment"
            ],
            "settings": {
                "foreground": "#3f3f3f"
            }
        },
        {
            "name": "JSDoc-style keywords",
            "scope": [
                "comment keyword.codetag.notation",
                "comment.block.documentation keyword",
                "comment.block.documentation storage.type.class"
            ],
            "settings": {
                "foreground": "#00f6d9"
            }
        },
        {
            "name": "JSDoc-style types",
            "scope": [
                "comment.block.documentation entity.name.type"
            ],
            "settings": {
                "foreground": "#8265ff",
                "fontStyle": "italic"
            }
        },
        {
            "name": "JSDoc-style type brackets",
            "scope": [
                "comment.block.documentation entity.name.type punctuation.definition.bracket"
            ],
            "settings": {
                "foreground": "#8265ff"
            }
        },
        {
            "name": "JSDoc-style comment parameters",
            "scope": [
                "comment.block.documentation variable"
            ],
            "settings": {
                "foreground": "#85ffe0",
                "fontStyle": "italic"
            }
        },
        {
            "name": "Constants",
            "scope": [
                "constant",
                "variable.other.constant"
            ],
            "settings": {
                "foreground": "#00eaff"
            }
        },
        {
            "name": "Constant escape sequences",
            "scope": [
                "constant.character.escape",
                "constant.character.string.escape",
                "constant.regexp"
            ],
            "settings": {
                "foreground": "#00f6d9"
            }
        },
        {
            "name": "HTML tags",
            "scope": [
                "entity.name.tag"
            ],
            "settings": {
                "foreground": "#00f6d9"
            }
        },
        {
            "name": "CSS attribute parent selectors ('&')",
            "scope": [
                "entity.other.attribute-name.parent-selector"
            ],
            "settings": {
                "foreground": "#00f6d9"
            }
        },
        {
            "name": "HTML/CSS attribute names",
            "scope": [
                "entity.other.attribute-name"
            ],
            "settings": {
                "foreground": "#0badff",
                "fontStyle": "italic"
            }
        },
        {
            "name": "Function names",
            "scope": [
                "entity.name.function",
                "meta.function-call.generic",
                "meta.function-call.object",
                "meta.function-call.php",
                "meta.function-call.static",
                "meta.method-call.java meta.method",
                "meta.method.groovy",
                "support.function.any-method.lua",
                "keyword.operator.function.infix"
            ],
            "settings": {
                "foreground": "#0badff"
            }
        },
        {
            "name": "Function parameters",
            "scope": [
                "entity.name.variable.parameter",
                "meta.at-rule.function variable",
                "meta.at-rule.mixin variable",
                "meta.function.arguments variable.other.php",
                "meta.selectionset.graphql meta.arguments.graphql variable.arguments.graphql",
                "variable.parameter"
            ],
            "settings": {
                "fontStyle": "italic",
                "foreground": "#85ffe0"
            }
        },
        {
            "name": "Decorators",
            "scope": [
                "meta.decorator variable.other.readwrite",
                "meta.decorator variable.other.property"
            ],
            "settings": {
                "foreground": "#0badff",
                "fontStyle": "italic"
            }
        },
        {
            "name": "Decorator Objects",
            "scope": [
                "meta.decorator variable.other.object"
            ],
            "settings": {
                "foreground": "#0badff"
            }
        },
        {
            "name": "Keywords",
            "scope": [
                "keyword",
                "punctuation.definition.keyword"
            ],
            "settings": {
                "foreground": "#00f6d9"
            }
        },
        {
            "name": "Keyword \"new\"",
            "scope": [
                "keyword.control.new",
                "keyword.operator.new"
            ],
            "settings": {
                "fontStyle": "bold"
            }
        },
        {
            "name": "Generic selectors (CSS/SCSS/Less/Stylus)",
            "scope": [
                "meta.selector"
            ],
            "settings": {
                "foreground": "#00f6d9"
            }
        },
        {
            "name": "Language Built-ins",
            "scope": [
                "support"
            ],
            "settings": {
                "fontStyle": "italic",
                "foreground": "#8265ff"
            }
        },
        {
            "name": "Built-in magic functions and constants",
            "scope": [
                "support.function.magic",
                "support.variable",
                "variable.other.predefined"
            ],
            "settings": {
                "fontStyle": "regular",
                "foreground": "#00eaff"
            }
        },
        {
            "name": "Built-in functions / properties",
            "scope": [
                "support.function",
                "support.type.property-name"
            ],
            "settings": {
                "fontStyle": "regular"
            }
        },
        {
            "name": "Separators (key/value, namespace, inheritance, pointer, hash, slice, etc)",
            "scope": [
                "constant.other.symbol.hashkey punctuation.definition.constant.ruby",
                "entity.other.attribute-name.placeholder punctuation",
                "entity.other.attribute-name.pseudo-class punctuation",
                "entity.other.attribute-name.pseudo-element punctuation",
                "meta.group.double.toml",
                "meta.group.toml",
                "meta.object-binding-pattern-variable punctuation.destructuring",
                "punctuation.colon.graphql",
                "punctuation.definition.block.scalar.folded.yaml",
                "punctuation.definition.block.scalar.literal.yaml",
                "punctuation.definition.block.sequence.item.yaml",
                "punctuation.definition.entity.other.inherited-class",
                "punctuation.function.swift",
                "punctuation.separator.dictionary.key-value",
                "punctuation.separator.hash",
                "punctuation.separator.inheritance",
                "punctuation.separator.key-value",
                "punctuation.separator.key-value.mapping.yaml",
                "punctuation.separator.namespace",
                "punctuation.separator.pointer-access",
                "punctuation.separator.slice",
                "string.unquoted.heredoc punctuation.definition.string",
                "support.other.chomping-indicator.yaml",
                "punctuation.separator.annotation"
            ],
            "settings": {
                "foreground": "#00f6d9"
            }
        },
        {
            "name": "Brackets, braces, parens, etc.",
            "scope": [
                "keyword.operator.other.powershell",
                "keyword.other.statement-separator.powershell",
                "meta.brace.round",
                "meta.function-call punctuation",
                "punctuation.definition.arguments.begin",
                "punctuation.definition.arguments.end",
                "punctuation.definition.entity.begin",
                "punctuation.definition.entity.end",
                "punctuation.definition.tag.cs",
                "punctuation.definition.type.begin",
                "punctuation.definition.type.end",
                "punctuation.section.scope.begin",
                "punctuation.section.scope.end",
                "storage.type.generic.java",
                "string.template meta.brace",
                "string.template punctuation.accessor"
            ],
            "settings": {
                "foreground": "#818181"
            }
        },
        {
            "name": "Variable interpolation operators",
            "scope": [
                "meta.string-contents.quoted.double punctuation.definition.variable",
                "punctuation.definition.interpolation.begin",
                "punctuation.definition.interpolation.end",
                "punctuation.definition.template-expression.begin",
                "punctuation.definition.template-expression.end",
                "punctuation.section.embedded.begin",
                "punctuation.section.embedded.coffee",
                "punctuation.section.embedded.end",
                "punctuation.section.embedded.end source.php",
                "punctuation.section.embedded.end source.ruby",
                "punctuation.definition.variable.makefile"
            ],
            "settings": {
                "foreground": "#00f6d9"
            }
        },
        {
            "name": "Keys (serializable languages)",
            "scope": [
                "entity.name.function.target.makefile",
                "entity.name.section.toml",
                "entity.name.tag.yaml",
                "variable.other.key.toml"
            ],
            "settings": {
                "foreground": "#8265ff"
            }
        },
        {
            "name": "Dates / timestamps (serializable languages)",
            "scope": [
                "constant.other.date",
                "constant.other.timestamp"
            ],
            "settings": {
                "foreground": "#85ffe0"
            }
        },
        {
            "name": "YAML aliases",
            "scope": [
                "variable.other.alias.yaml"
            ],
            "settings": {
                "fontStyle": "italic underline",
                "foreground": "#0badff"
            }
        },
        {
            "name": "Storage",
            "scope": [
                "storage",
                "meta.implementation storage.type.objc",
                "meta.interface-or-protocol storage.type.objc",
                "source.groovy storage.type.def"
            ],
            "settings": {
                "fontStyle": "regular",
                "foreground": "#00f6d9"
            }
        },
        {
            "name": "Types",
            "scope": [
                "entity.name.type",
                "keyword.primitive-datatypes.swift",
                "keyword.type.cs",
                "meta.protocol-list.objc",
                "meta.return-type.objc",
                "source.go storage.type",
                "source.groovy storage.type",
                "source.java storage.type",
                "source.powershell entity.other.attribute-name",
                "storage.class.std.rust",
                "storage.type.attribute.swift",
                "storage.type.c",
                "storage.type.core.rust",
                "storage.type.cs",
                "storage.type.groovy",
                "storage.type.objc",
                "storage.type.php",
                "storage.type.haskell",
                "storage.type.ocaml"
            ],
            "settings": {
                "fontStyle": "italic",
                "foreground": "#8265ff"
            }
        },
        {
            "name": "Generics, templates, and mapped type declarations",
            "scope": [
                "entity.name.type.type-parameter",
                "meta.indexer.mappedtype.declaration entity.name.type",
                "meta.type.parameters entity.name.type"
            ],
            "settings": {
                "foreground": "#85ffe0"
            }
        },
        {
            "name": "Modifiers",
            "scope": [
                "storage.modifier"
            ],
            "settings": {
                "foreground": "#00f6d9"
            }
        },
        {
            "name": "RegExp string",
            "scope": [
                "string.regexp",
                "constant.other.character-class.set.regexp",
                "constant.character.escape.backslash.regexp"
            ],
            "settings": {
                "foreground": "#"
            }
        },
        {
            "name": "Non-capture operators",
            "scope": [
                "punctuation.definition.group.capture.regexp"
            ],
            "settings": {
                "foreground": "#00f6d9"
            }
        },
        {
            "name": "RegExp start and end characters",
            "scope": [
                "string.regexp punctuation.definition.string.begin",
                "string.regexp punctuation.definition.string.end"
            ],
            "settings": {
                "foreground": "#ff29a8"
            }
        },
        {
            "name": "Character group",
            "scope": [
                "punctuation.definition.character-class.regexp"
            ],
            "settings": {
                "foreground": "#8265ff"
            }
        },
        {
            "name": "Capture groups",
            "scope": [
                "punctuation.definition.group.regexp"
            ],
            "settings": {
                "foreground": "#85ffe0"
            }
        },
        {
            "name": "Assertion operators",
            "scope": [
                "punctuation.definition.group.assertion.regexp",
                "keyword.operator.negation.regexp"
            ],
            "settings": {
                "foreground": "#ff29a8"
            }
        },
        {
            "name": "Positive lookaheads",
            "scope": [
                "meta.assertion.look-ahead.regexp"
            ],
            "settings": {
                "foreground": "#0badff"
            }
        },
        {
            "name": "Strings",
            "scope": [
                "string"
            ],
            "settings": {
                "foreground": "#"
            }
        },
        {
            "name": "String quotes (temporary vscode fix)",
            "scope": [
                "punctuation.definition.string.begin",
                "punctuation.definition.string.end"
            ],
            "settings": {
                "foreground": "#f0ffaa"
            }
        },
        {
            "name": "Property quotes (temporary vscode fix)",
            "scope": [
                "punctuation.support.type.property-name.begin",
                "punctuation.support.type.property-name.end"
            ],
            "settings": {
                "foreground": "#00eaff"
            }
        },
        {
            "name": "Docstrings",
            "scope": [
                "string.quoted.docstring.multi",
                "string.quoted.docstring.multi.python punctuation.definition.string.begin",
                "string.quoted.docstring.multi.python punctuation.definition.string.end",
                "string.quoted.docstring.multi.python constant.character.escape"
            ],
            "settings": {
                "foreground": "#3f3f3f"
            }
        },
        {
            "name": "Variables and object properties",
            "scope": [
                "variable",
                "constant.other.key.perl",
                "support.variable.property",
                "variable.other.constant.js",
                "variable.other.constant.ts",
                "variable.other.constant.tsx"
            ],
            "settings": {
                "foreground": "#818181"
            }
        },
        {
            "name": "Destructuring / aliasing reference name (LHS)",
            "scope": [
                "meta.import variable.other.readwrite",
                "meta.object-binding-pattern-variable variable.object.property",
                "meta.variable.assignment.destructured.object.coffee variable"
            ],
            "settings": {
                "fontStyle": "italic",
                "foreground": "#85ffe0"
            }
        },
        {
            "name": "Destructuring / aliasing variable name (RHS)",
            "scope": [
                "meta.import variable.other.readwrite.alias",
                "meta.export variable.other.readwrite.alias",
                "meta.variable.assignment.destructured.object.coffee variable variable"
            ],
            "settings": {
                "fontStyle": "normal",
                "foreground": "#818181"
            }
        },
        {
            "name": "GraphQL keys",
            "scope": [
                "meta.selectionset.graphql variable"
            ],
            "settings": {
                "foreground": "#"
            }
        },
        {
            "name": "GraphQL function arguments",
            "scope": [
                "meta.selectionset.graphql meta.arguments variable"
            ],
            "settings": {
                "foreground": "#818181"
            }
        },
        {
            "name": "GraphQL fragment name (definition)",
            "scope": [
                "entity.name.fragment.graphql",
                "variable.fragment.graphql"
            ],
            "settings": {
                "foreground": "#8265ff"
            }
        },
        {
            "name": "Edge cases (foreground color resets)",
            "scope": [
                "constant.other.symbol.hashkey.ruby",
                "keyword.operator.dereference.java",
                "keyword.operator.navigation.groovy",
                "meta.scope.for-loop.shell punctuation.definition.string.begin",
                "meta.scope.for-loop.shell punctuation.definition.string.end",
                "meta.scope.for-loop.shell string",
                "storage.modifier.import",
                "punctuation.section.embedded.begin.tsx",
                "punctuation.section.embedded.end.tsx",
                "punctuation.section.embedded.begin.jsx",
                "punctuation.section.embedded.end.jsx",
                "punctuation.separator.list.comma.css",
                "constant.language.empty-list.haskell"
            ],
            "settings": {
                "foreground": "#818181"
            }
        },
        {
            "name": "Shell variables prefixed with \"$\" (edge case)",
            "scope": [
                "source.shell variable.other"
            ],
            "settings": {
                "foreground": "#00eaff"
            }
        },
        {
            "name": "Powershell constants mistakenly scoped to `support`, rather than `constant` (edge)",
            "scope": [
                "support.constant"
            ],
            "settings": {
                "fontStyle": "normal",
                "foreground": "#00eaff"
            }
        },
        {
            "name": "Makefile prerequisite names",
            "scope": [
                "meta.scope.prerequisites.makefile"
            ],
            "settings": {
                "foreground": "#"
            }
        },
        {
            "name": "SCSS attibute selector strings",
            "scope": [
                "meta.attribute-selector.scss"
            ],
            "settings": {
                "foreground": "#"
            }
        },
        {
            "name": "SCSS attribute selector brackets",
            "scope": [
                "punctuation.definition.attribute-selector.end.bracket.square.scss",
                "punctuation.definition.attribute-selector.begin.bracket.square.scss"
            ],
            "settings": {
                "foreground": "#818181"
            }
        },
        {
            "name": "Haskell Pragmas",
            "scope": [
                "meta.preprocessor.haskell"
            ],
            "settings": {
                "foreground": "#3f3f3f"
            }
        }
    ]
}
